rfl/web/__init__.py
rfl/web/tokens.py
rfl_web-1.6.0.dist-info/METADATA
rfl_web-1.6.0.dist-info/WHEEL
rfl_web-1.6.0.dist-info/top_level.txt
rfl_web-1.6.0.dist-info/RECORD
