Metadata-Version: 2.4
Name: RFL.web
Version: 1.6.0
Summary: Rackslab Foundation Library: web package
Author-email: Rémi Palancher <remi@rackslab.io>
License-Expression: LGPL-3.0-or-later
Project-URL: Homepage, https://github.com/rackslab/RFL
Project-URL: Bug Tracker, https://github.com/rackslab/RFL/issues
Keywords: utility,basic
Classifier: Development Status :: 5 - Production/Stable
Classifier: Environment :: Console
Classifier: Intended Audience :: System Administrators
Classifier: Programming Language :: Python :: 3
Classifier: Topic :: System :: Systems Administration
Requires-Python: >=3.6
Requires-Dist: Flask
Requires-Dist: RFL.permissions
Requires-Dist: RFL.authentication
